{"name":"build-javascript","namedChunkGroups":{"polyfill":{"name":"polyfill","assets":[{"name":"webpack-runtime-50e530fb655aed710cdc.js","size":4254},{"name":"polyfill-10e3ae93bfdcb1b622c9.js","size":85830}],"filteredAssets":0,"assetsSize":90084,"filteredAuxiliaryAssets":2,"auxiliaryAssetsSize":225318},"app":{"name":"app","assets":[{"name":"webpack-runtime-50e530fb655aed710cdc.js","size":4254},{"name":"framework-b5e1d5f0f9d87093ac0a.js","size":128679},{"name":"app-29b56e789d17755b485a.js","size":51237}],"filteredAssets":0,"assetsSize":184170,"filteredAuxiliaryAssets":3,"auxiliaryAssetsSize":550722},"component---src-pages-index-js":{"name":"component---src-pages-index-js","assets":[{"name":"styles.31d6cfe0d16ae931b73c.css","size":0},{"name":"component---src-pages-index-js-58e1ff866b933053df49.js","size":2535}],"filteredAssets":0,"assetsSize":2535,"filteredAuxiliaryAssets":3,"auxiliaryAssetsSize":755580}},"assetsByChunkName":{"polyfill":["webpack-runtime-50e530fb655aed710cdc.js","polyfill-10e3ae93bfdcb1b622c9.js"],"app":["webpack-runtime-50e530fb655aed710cdc.js","framework-b5e1d5f0f9d87093ac0a.js","app-29b56e789d17755b485a.js"],"component---src-pages-index-js":["styles.31d6cfe0d16ae931b73c.css","component---src-pages-index-js-58e1ff866b933053df49.js"]},"childAssetsByChunkName":{}}